MANIFEST.in
setup.py
Products/__init__.py
Products.SilvaFind.egg-info/PKG-INFO
Products.SilvaFind.egg-info/SOURCES.txt
Products.SilvaFind.egg-info/dependency_links.txt
Products.SilvaFind.egg-info/namespace_packages.txt
Products.SilvaFind.egg-info/not-zip-safe
Products.SilvaFind.egg-info/requires.txt
Products.SilvaFind.egg-info/top_level.txt
Products/SilvaFind/HISTORY.txt
Products/SilvaFind/README.txt
Products/SilvaFind/SilvaFind.png
Products/SilvaFind/SilvaFind.py
Products/SilvaFind/__init__.py
Products/SilvaFind/configure.zcml
Products/SilvaFind/findservice.png
Products/SilvaFind/findservice.py
Products/SilvaFind/ftesting.zcml
Products/SilvaFind/globalschema.py
Products/SilvaFind/interfaces.py
Products/SilvaFind/query.py
Products/SilvaFind/schema.py
Products/SilvaFind/testing.py
Products/SilvaFind/SilvaFind_templates/findeditview.pt
Products/SilvaFind/SilvaFind_templates/findsitemap.cpt
Products/SilvaFind/SilvaFind_templates/findview.pt
Products/SilvaFind/criterion/__init__.py
Products/SilvaFind/criterion/criterion.py
Products/SilvaFind/criterion/widgets/__init__.py
Products/SilvaFind/criterion/widgets/default.py
Products/SilvaFind/criterion/widgets/fulltext.py
Products/SilvaFind/criterion/widgets/metadata.py
Products/SilvaFind/criterion/widgets/metatype.py
Products/SilvaFind/criterion/widgets/path.py
Products/SilvaFind/criterion/widgets/templates/daterangecriterion.cpt
Products/SilvaFind/criterion/widgets/templates/integerrangecriterion.cpt
Products/SilvaFind/criterion/widgets/templates/metatypecriterion.cpt
Products/SilvaFind/criterion/widgets/templates/pathcriterion.cpt
Products/SilvaFind/i18n/__init__.py
Products/SilvaFind/i18n/silvafind.pot
Products/SilvaFind/i18n/da/LC_MESSAGES/silvafind.mo
Products/SilvaFind/i18n/da/LC_MESSAGES/silvafind.po
Products/SilvaFind/i18n/de/LC_MESSAGES/silvafind.mo
Products/SilvaFind/i18n/de/LC_MESSAGES/silvafind.po
Products/SilvaFind/i18n/en/LC_MESSAGES/silvafind.mo
Products/SilvaFind/i18n/en/LC_MESSAGES/silvafind.po
Products/SilvaFind/i18n/es/LC_MESSAGES/silvafind.mo
Products/SilvaFind/i18n/es/LC_MESSAGES/silvafind.po
Products/SilvaFind/i18n/fr/LC_MESSAGES/silvafind.mo
Products/SilvaFind/i18n/fr/LC_MESSAGES/silvafind.po
Products/SilvaFind/i18n/he/LC_MESSAGES/silvafind.mo
Products/SilvaFind/i18n/he/LC_MESSAGES/silvafind.po
