Metadata-Version: 1.1
Name: Products.SilvaFind
Version: 3.0.4
Summary: Search extension for Silva CMS
Home-page: https://github.com/silvacms/Products.SilvaFind
Author: Infrae
Author-email: info@infrae.com
License: BSD
Keywords: silva search zope2
Platform: UNKNOWN
Classifier: Framework :: Zope2
Classifier: Programming Language :: Python
Classifier: Topic :: Software Development :: Libraries :: Python Modules
